<mvc:View
    controllerName="myinbox.controller.View1"
    xmlns:mvc="sap.ui.core.mvc"
    xmlns="sap.m"
    xmlns:c="sap.ui.core"
    displayBlock="true"
    height="100%"
    busyIndicatorDelay="0"
>
    <Page>
        <content>
            <VBox
                id="gifContainer"
                justifyContent="Center"
                alignItems="Center"
                width="100%"
                height="100%"
            >
                <Image
                    id="gifImage"
                    src="https://reportsvault.com/public/assets/images/audit-fig-1.png"
                    width="300px"
                    height="300px"
                    alt="Loading Animation"
                />
                <Text ></Text>
                <Text ></Text>
                
                <Title text="Select a leave record"  />
                <Text text="Select a leave application to display information"></Text>
            </VBox>
        </content>
    </Page>
</mvc:View>
